mkprj.py
mkprj-0.1.1.dist-info/METADATA
mkprj-0.1.1.dist-info/WHEEL
mkprj-0.1.1.dist-info/entry_points.txt
mkprj-0.1.1.dist-info/top_level.txt
mkprj-0.1.1.dist-info/RECORD
