Metadata-Version: 2.1
Name: mkprj
Version: 0.1.1
Summary: Easily create new Python projects.
Home-page: https://github.com/tomplex/mkprj
Author: Tom Caruso
Author-email: carusot42@gmail.com
License: MIT
Platform: UNKNOWN
Classifier: License :: OSI Approved :: MIT License
Classifier: Programming Language :: Python
Classifier: Programming Language :: Python :: 3
Classifier: Programming Language :: Python :: 3.6
Classifier: Programming Language :: Python :: Implementation :: CPython
Classifier: Programming Language :: Python :: Implementation :: PyPy
Requires-Python: >=3.5.0
